setup.py
Remtii/__init__.py
Remtii/a.py
Remtii.egg-info/PKG-INFO
Remtii.egg-info/SOURCES.txt
Remtii.egg-info/dependency_links.txt
Remtii.egg-info/top_level.txt