Metadata-Version: 1.1
Name: Remtii
Version: 0.1
Summary: Remtii Python Package
Home-page: UNKNOWN
Author: Remtii
Author-email: <radvisia@gmail.com>
License: UNKNOWN
Keywords: remtii,python,package,rpp
Platform: UNKNOWN
Classifier: Development Status :: 1 - Planning
Classifier: Intended Audience :: Developers
Classifier: Programming Language :: Python :: 3
Classifier: Operating System :: Unix
Classifier: Operating System :: MacOS :: MacOS X
Classifier: Operating System :: Microsoft :: Windows
